setup.py
superestart/__init__.py
superestart/main.py
superestart.egg-info/PKG-INFO
superestart.egg-info/SOURCES.txt
superestart.egg-info/dependency_links.txt
superestart.egg-info/entry_points.txt
superestart.egg-info/not-zip-safe
superestart.egg-info/requires.txt
superestart.egg-info/top_level.txt