Metadata-Version: 1.1
Name: superestart
Version: 1.1.0
Summary: A supervisord plugin used to autorestart program by specific time
Home-page: https://github.com/fatelei/superestart
Author: Wang Lei
Author-email: fatelei@gmail.com
License: BSD License
Platform: UNKNOWN
Classifier: Development Status :: 5 - Production/Stable
Classifier: Environment :: Console
Classifier: Environment :: Web Environment
Classifier: Intended Audience :: Developers
Classifier: License :: OSI Approved :: BSD License
Classifier: Programming Language :: Python :: 2.7
Classifier: Topic :: Software Development :: Libraries
